ssb_sirius_dash/__init__.py
ssb_sirius_dash/__main__.py
ssb_sirius_dash/functions.py
ssb_sirius_dash/hb_method_aio.py
ssb_sirius_dash/kostra_r_wrapper.py
ssb_sirius_dash/py.typed
ssb_sirius_dash/sunburst_aio.py
ssb_sirius_dash-0.1.3.dist-info/LICENSE
ssb_sirius_dash-0.1.3.dist-info/METADATA
ssb_sirius_dash-0.1.3.dist-info/WHEEL
ssb_sirius_dash-0.1.3.dist-info/entry_points.txt
ssb_sirius_dash-0.1.3.dist-info/RECORD
