Metadata-Version: 2.1
Name: ssb-sirius-dash
Version: 0.1.3
Summary: SSB Sirius Dash
Home-page: https://github.com/statisticsnorway/ssb-sirius-dash
License: MIT
Author: Stian Elisenberg
Author-email: seg@ssb.no
Requires-Python: >=3.9,<4.0
Classifier: Development Status :: 1 - Planning
Classifier: License :: OSI Approved :: MIT License
Classifier: Programming Language :: Python :: 3
Classifier: Programming Language :: Python :: 3.9
Classifier: Programming Language :: Python :: 3.10
Classifier: Programming Language :: Python :: 3.11
Classifier: Programming Language :: Python :: 3.12
Requires-Dist: click (>=8.0.1)
Requires-Dist: dash (>=2.15.0,<3.0.0)
Requires-Dist: dash-bootstrap-components (>=1.5.0,<2.0.0)
Requires-Dist: pandas (>=2.2.0,<3.0.0)
Requires-Dist: rpy2 (>=3.5.15,<4.0.0)
Project-URL: Changelog, https://github.com/statisticsnorway/ssb-sirius-dash/releases
Project-URL: Documentation, https://statisticsnorway.github.io/ssb-sirius-dash
Project-URL: Repository, https://github.com/statisticsnorway/ssb-sirius-dash
